wtk/__init__.py
wtk/requirements.txt
wtk/utilities.py
wtk-0.2.1.3.dist-info/WHEEL
wtk-0.2.1.3.dist-info/METADATA
wtk-0.2.1.3.dist-info/RECORD
