Metadata-Version: 2.1
Name: wtk
Version: 0.2.1.3
Summary: A Wasserstein Subsequence Kernel for Time Series
Home-page: https://github.com/BorgwardtLab/WTK
License: UNKNOWN
Author: Christian Bock
Author-email: christian.bock@bsse.ethz.ch
Requires-Python: >=3.6
Classifier: License :: OSI Approved :: MIT License
Classifier: Programming Language :: Python :: 3
Requires-Dist: Cython
Requires-Dist: POT
Requires-Dist: numpy
Requires-Dist: scikit-learn
Project-URL: Issues, https://github.com/BorgwardtLab/WTK/issues
